biothings_typed_client/__init__.py
biothings_typed_client/abstract_client.py
biothings_typed_client/chem.py
biothings_typed_client/clear_cache.py
biothings_typed_client/cli.py
biothings_typed_client/genes.py
biothings_typed_client/genesets.py
biothings_typed_client/taxons.py
biothings_typed_client/variants.py
biothings_typed_client-0.0.9.dist-info/METADATA
biothings_typed_client-0.0.9.dist-info/WHEEL
biothings_typed_client-0.0.9.dist-info/entry_points.txt
biothings_typed_client-0.0.9.dist-info/licenses/LICENSE
biothings_typed_client-0.0.9.dist-info/RECORD
