Metadata-Version: 2.4
Name: biothings-typed-client
Version: 0.0.9
Summary: A strongly-typed Python wrapper around the BioThings Client library, providing type safety and better IDE support through Python's type hints and Pydantic models.
Author-email: antonkulaga <antonkulaga@gmail.com>
License-File: LICENSE
Requires-Python: >=3.10
Requires-Dist: biothings-client[caching]>=0.4.1
Requires-Dist: pandas>=2.1.1
Requires-Dist: pydantic>=2.11.4
Requires-Dist: pyld>=2.0.4
Requires-Dist: rich>=14.0.0
Requires-Dist: typer>=0.16.0
